mmdet_add/__init__.py
mmdet_add/version.py
mmdet_add/datasets/__init__.py
mmdet_add/datasets/coco.py
mmdet_add/datasets/voc.py
mmdet_add/models/__init__.py
mmdet_add/models/dense_heads/__init__.py
mmdet_add/models/dense_heads/efficient_head.py
mmdet_add/models/detectors/__init__.py
mmdet_add/models/detectors/efficientdet.py
mmdet_add/models/necks/__init__.py
mmdet_add/models/necks/bifpn.py
mmdet_add/models/utils/__init__.py
mmdet_add/models/utils/combine.py
mmdet_add/models/utils/dpconv_layer.py
mmdet_add/utils/__init__.py
mmdet_add/utils/collect_env.py
mmdet_add-0.1.0.dist-info/DESCRIPTION.rst
mmdet_add-0.1.0.dist-info/METADATA
mmdet_add-0.1.0.dist-info/RECORD
mmdet_add-0.1.0.dist-info/WHEEL
mmdet_add-0.1.0.dist-info/metadata.json
mmdet_add-0.1.0.dist-info/top_level.txt
